trinkgelage/__init__.py
trinkgelage/_version.py
trinkgelage/_version.pyi
trinkgelage/py.typed
trinkgelage/data/grasp_cup_1.csv
trinkgelage/data/grasp_faucet.csv
trinkgelage/data/left_idle.csv
trinkgelage/data/level_cup.csv
trinkgelage/data/move_cup_to_faucet.csv
trinkgelage/data/open_faucet.csv
trinkgelage/data/place_cup.csv
trinkgelage/data/post_place_cup.csv
trinkgelage/data/pre_grasp_faucet.csv
trinkgelage/data/right_idle.csv
trinkgelage/demo/__init__.py
trinkgelage/demo/control.py
trinkgelage/demo/start_button.py
trinkgelage/launchers/__init__.py
trinkgelage/launchers/demo.py
trinkgelage/robot/__init__.py
trinkgelage/robot/actions.py
trinkgelage/robot/utils.py
trinkgelage-1.0.1.dist-info/METADATA
trinkgelage-1.0.1.dist-info/WHEEL
trinkgelage-1.0.1.dist-info/entry_points.txt
trinkgelage-1.0.1.dist-info/licenses/LICENSE
trinkgelage-1.0.1.dist-info/RECORD
