Metadata-Version: 2.3
Name: trinkgelage
Version: 1.0.1
Summary: A beer tapping demo.
Project-URL: Homepage, https://github.com/tum-robotics/trinkgelage
Project-URL: Bug Tracker, https://github.com/tum-robotics/trinkgelage/issues
Project-URL: Discussions, https://github.com/tum-robotics/trinkgelage/discussions
Project-URL: Changelog, https://github.com/tum-robotics/trinkgelage/releases
Author-email: Jean Elsner <jean.elsner@tum.de>
License: 
License-File: LICENSE
Classifier: Development Status :: 1 - Planning
Classifier: Intended Audience :: Developers
Classifier: Intended Audience :: Science/Research
Classifier: License :: OSI Approved :: Apache Software License
Classifier: Operating System :: OS Independent
Classifier: Programming Language :: Python
Classifier: Programming Language :: Python :: 3
Classifier: Programming Language :: Python :: 3 :: Only
Classifier: Programming Language :: Python :: 3.8
Classifier: Programming Language :: Python :: 3.9
Classifier: Programming Language :: Python :: 3.10
Classifier: Programming Language :: Python :: 3.11
Classifier: Programming Language :: Python :: 3.12
Classifier: Topic :: Scientific/Engineering
Classifier: Typing :: Typed
Requires-Python: >=3.8
Requires-Dist: panda-python
Requires-Dist: pyserial
Requires-Dist: python-statemachine
Requires-Dist: simple-term-menu
Provides-Extra: dev
Requires-Dist: pytest-cov>=3; extra == 'dev'
Requires-Dist: pytest>=6; extra == 'dev'
Provides-Extra: docs
Requires-Dist: furo>=2023.08.17; extra == 'docs'
Requires-Dist: myst-parser>=0.13; extra == 'docs'
Requires-Dist: sphinx-autodoc-typehints; extra == 'docs'
Requires-Dist: sphinx-copybutton; extra == 'docs'
Requires-Dist: sphinx-reredirects; extra == 'docs'
Requires-Dist: sphinx>=7.0; extra == 'docs'
Provides-Extra: test
Requires-Dist: pytest-cov>=3; extra == 'test'
Requires-Dist: pytest>=6; extra == 'test'
